Metadata-Version: 2.4
Name: comradecircle-sdk
Version: 0.1.0a20251021160645
Summary: Python SDK for ComradeCircle API - Social communication and creator economy platform integration
Project-URL: Homepage, https://github.com/algoshred/comradecircle-sdk-python
Project-URL: Documentation, https://docs.algoshred.com/sdk/python
Project-URL: Repository, https://github.com/algoshred/comradecircle-sdk-python
Project-URL: Issues, https://github.com/algoshred/comradecircle-sdk-python/issues
Project-URL: Changelog, https://github.com/algoshred/comradecircle-sdk-python/blob/main/CHANGELOG.md
Author-email: "Vignesh T.V" <vignesh@algoshred.com>
Maintainer-email: "Vignesh T.V" <vignesh@algoshred.com>
License: Copyright (c) 2025 Burdenoff Consultancy Services Private Limited, Algoshred Technologies Private Limited and all sister companies.
License-File: LICENSE
Keywords: algoshred,api-client,community-management,comradecircle,creator-economy,graphql,python,real-time-communication,sdk,social-platform
Classifier: Development Status :: 3 - Alpha
Classifier: Intended Audience :: Developers
Classifier: License :: Other/Proprietary License
Classifier: Operating System :: OS Independent
Classifier: Programming Language :: Python :: 3
Classifier: Programming Language :: Python :: 3.8
Classifier: Programming Language :: Python :: 3.9
Classifier: Programming Language :: Python :: 3.10
Classifier: Programming Language :: Python :: 3.11
Classifier: Programming Language :: Python :: 3.12
Classifier: Topic :: Internet :: WWW/HTTP :: HTTP Servers
Classifier: Topic :: Software Development :: Libraries :: Application Frameworks
Classifier: Topic :: Software Development :: Libraries :: Python Modules
Requires-Python: >=3.8
Requires-Dist: httpx>=0.24.0
Requires-Dist: typing-extensions>=4.0.0; python_version < '3.11'
Provides-Extra: dev
Requires-Dist: black>=23.0.0; extra == 'dev'
Requires-Dist: flake8>=6.0.0; extra == 'dev'
Requires-Dist: isort>=5.12.0; extra == 'dev'
Requires-Dist: mypy>=1.0.0; extra == 'dev'
Requires-Dist: pre-commit>=3.0.0; extra == 'dev'
Requires-Dist: pytest-asyncio>=0.21.0; extra == 'dev'
Requires-Dist: pytest-cov>=4.0.0; extra == 'dev'
Requires-Dist: pytest>=7.0.0; extra == 'dev'
Provides-Extra: docs
Requires-Dist: sphinx-autodoc-typehints>=1.19.0; extra == 'docs'
Requires-Dist: sphinx-rtd-theme>=1.2.0; extra == 'docs'
Requires-Dist: sphinx>=6.0.0; extra == 'docs'
Provides-Extra: test
Requires-Dist: httpx[testing]>=0.24.0; extra == 'test'
Requires-Dist: pytest-asyncio>=0.21.0; extra == 'test'
Requires-Dist: pytest-cov>=4.0.0; extra == 'test'
Requires-Dist: pytest>=7.0.0; extra == 'test'
